{
  "version": "2.0",
  "pipeline_stage": "enriched",
  "title": "Simon-conflict Task.",
  "description": "This dataset comprises EEG recordings from 146 participants (98 with Parkinson's disease and 48 healthy controls) performing a Simon conflict task. Participants responded to color-coded stimuli presented laterally on a screen using a 64-channel BrainVision EEG system. The task manipulated spatial congruency between stimulus location and required response hand, enabling investigation of conflict processing and motor control mechanisms in both patient and control populations.",
  "methods_description": "EEG data were acquired using a 64-channel BrainVision cap during performance of a Simon task. Stimuli (yellow, red, cyan, or blue) were presented on the left or right side of the screen. Participants pressed left or right keys based on stimulus color (yellow/red → left; cyan/blue → right), creating spatially congruent and incongruent trial conditions. Data were analyzed separately for congruent and incongruent trials. All research protocols were approved by the University of Iowa Human Subjects Review Board (IRB# 201707828). This research was supported by NIH grants P20NS123151 and R01NS100849, and NRSA F32AG069445-01.",
  "license": "CC0",
  "dataset_type": "raw",
  "authors": {
    "Arun Singh arun.singh@usd.edu": {},
    "Rachel Cole rachel-cole@uiowa.edu": {},
    "Arturo Espinoza arturo-espinoza@uiowa.edu": {},
    "Jan R Wessel jan-wessel@uiowa.edu": {},
    "Jim Cavanagh jcavanagh@unm.edu": {},
    "Nandakumar Narayanan nandakumar-narayanan@uiowa.edu": {}
  },
  "keywords": [
    {
      "term": "EEG"
    },
    {
      "term": "Simon task"
    },
    {
      "term": "conflict processing"
    },
    {
      "term": "Parkinson's disease"
    },
    {
      "term": "healthy controls"
    },
    {
      "term": "motor control"
    },
    {
      "term": "event-related potentials"
    },
    {
      "term": "response inhibition"
    },
    {
      "term": "error monitoring"
    },
    {
      "term": "BrainVision"
    },
    {
      "term": "spatial congruency"
    }
  ],
  "related_identifiers": [
    {
      "identifier": "10.1101/2022.07.26.22278079",
      "identifier_type": "DOI",
      "relation_type": "References"
    },
    {
      "identifier": "https://github.com/nemarDatasets/on004580",
      "identifier_type": "URL",
      "relation_type": "IsDescribedBy"
    },
    {
      "identifier": "https://nemar.org/dataexplorer/detail?dataset_id=on004580",
      "identifier_type": "URL",
      "relation_type": "IsDescribedBy"
    },
    {
      "identifier": "10.18112/openneuro.ds004580.v1.0.0",
      "identifier_type": "DOI",
      "relation_type": "IsDerivedFrom"
    }
  ],
  "funding_references": [
    {
      "funder_name": "and NRSA F32 AG069445-01 to RC. All research protocols were approved by the University of Iowa"
    },
    {
      "funder_name": " Human Subjects Review Board (IRB# 201707828)."
    },
    {
      "funder_name": "NIH",
      "award_number": "P20NS123151"
    },
    {
      "funder_name": "NIH",
      "award_number": "R01NS100849"
    },
    {
      "funder_name": "NIH",
      "award_number": "F32AG069445-01"
    },
    {
      "funder_name": "NIH",
      "award_number": "F32AG069445"
    }
  ],
  "resource_type_specific": "Neuroimaging Dataset",
  "modalities": [
    "beh",
    "eeg"
  ],
  "sizes": [
    "17.0 GB (295 files)"
  ],
  "formats": [
    ".fdt",
    ".json",
    ".md",
    ".set",
    ".tsv",
    ".yml"
  ],
  "source_hash": "11f8fd7fbd0c97ec836d043a21a234b3be351d72661481fdecf241edf52c76e0"
}